agent_evaluator/__init__.py
agent_evaluator/evaluator.py
agent_evaluator/opik_evaluation.py
agent_evaluator/opik_setup.py
agent_evaluator/optimizer.py
agent_evaluator-0.1.0.dist-info/METADATA
agent_evaluator-0.1.0.dist-info/WHEEL
agent_evaluator-0.1.0.dist-info/top_level.txt
agent_evaluator-0.1.0.dist-info/RECORD
