Metadata-Version: 2.4
Name: agent_evaluator
Version: 0.1.0
Requires-Dist: google-adk
Requires-Dist: opik
Requires-Dist: google-generativeai
Requires-Dist: python-dotenv
Requires-Dist: litellm
Requires-Dist: opik-optimizer
Requires-Dist: numpy
Requires-Dist: scipy
Requires-Dist: sentence-transformers
Requires-Dist: openai
